interactive_terminal/__init__.py
interactive_terminal/interactive_terminal.py
tests/__init__.py
tests/test_interactive_terminal.py
interactive_terminal-0.2.dist-info/LICENSE
interactive_terminal-0.2.dist-info/METADATA
interactive_terminal-0.2.dist-info/WHEEL
interactive_terminal-0.2.dist-info/top_level.txt
interactive_terminal-0.2.dist-info/RECORD
