Metadata-Version: 2.1
Name: interactive-terminal
Version: 0.2
Summary: An interactive terminal question and answer module.
Author: Aiden Metcalfe
Author-email: avaartshop@outlook.com
Classifier: Development Status :: 3 - Alpha
Classifier: Intended Audience :: Developers
Classifier: License :: OSI Approved :: MIT License
Classifier: Programming Language :: Python :: 3
License-File: LICENSE
Requires-Dist: colorama
